snookey2.py
Snookey2-3.2.1.dist-info/LICENSE.txt
Snookey2-3.2.1.dist-info/METADATA
Snookey2-3.2.1.dist-info/WHEEL
Snookey2-3.2.1.dist-info/entry_points.txt
Snookey2-3.2.1.dist-info/top_level.txt
Snookey2-3.2.1.dist-info/RECORD
