Metadata-Version: 2.1
Name: Snookey2
Version: 3.2.1
Summary: Stream on RPAN on PC easily using OBS and this module!
Home-page: https://github.com/IOnlyPlayAsDrift/Snookey2
Author: IOnlyPlayAsDrift
License: UNKNOWN
Platform: UNKNOWN
Requires-Dist: pytz
Requires-Dist: requests
Requires-Dist: pypresence
Requires-Dist: praw
